flowcon/__init__.py
flowcon/CNF/__init__.py
flowcon/CNF/cnf.py
flowcon/CNF/neural_odes/__init__.py
flowcon/CNF/neural_odes/odefunc.py
flowcon/CNF/neural_odes/squeeze.py
flowcon/CNF/neural_odes/util.py
flowcon/CNF/neural_odes/diffeq_layers/__init__.py
flowcon/CNF/neural_odes/diffeq_layers/basic.py
flowcon/CNF/neural_odes/diffeq_layers/container.py
flowcon/CNF/neural_odes/diffeq_layers/resnet.py
flowcon/CNF/neural_odes/diffeq_layers/wrappers.py
flowcon/CNF/neural_odes/wrappers/__init__.py
flowcon/CNF/neural_odes/wrappers/cnf_regularization.py
flowcon/datasets/__init__.py
flowcon/datasets/base.py
flowcon/datasets/plane.py
flowcon/datasets/uci/__init__.py
flowcon/datasets/uci/bsds300.py
flowcon/datasets/uci/download.py
flowcon/datasets/uci/gas.py
flowcon/datasets/uci/hepmass.py
flowcon/datasets/uci/miniboone.py
flowcon/datasets/uci/power.py
flowcon/datasets/uci/uci.py
flowcon/datasets/uci/utils.py
flowcon/distributions/__init__.py
flowcon/distributions/base.py
flowcon/distributions/discrete.py
flowcon/distributions/mixture.py
flowcon/distributions/normal.py
flowcon/distributions/uniform.py
flowcon/flows/__init__.py
flowcon/flows/autoregressive.py
flowcon/flows/base.py
flowcon/flows/realnvp.py
flowcon/nn/__init__.py
flowcon/nn/nde/__init__.py
flowcon/nn/nde/made.py
flowcon/nn/nets/__init__.py
flowcon/nn/nets/activations.py
flowcon/nn/nets/extended_basic_nets.py
flowcon/nn/nets/invertible_densenet.py
flowcon/nn/nets/lipschitz_dense.py
flowcon/nn/nets/mlp.py
flowcon/nn/nets/nets_util.py
flowcon/nn/nets/resnet.py
flowcon/nn/nets/spectral_norm.py
flowcon/transforms/__init__.py
flowcon/transforms/adaptive_sigmoids.py
flowcon/transforms/base.py
flowcon/transforms/conditional.py
flowcon/transforms/conv.py
flowcon/transforms/coupling.py
flowcon/transforms/linear.py
flowcon/transforms/lu.py
flowcon/transforms/made.py
flowcon/transforms/nonlinearities.py
flowcon/transforms/normalization.py
flowcon/transforms/orthogonal.py
flowcon/transforms/permutations.py
flowcon-0.0.4.dist-info/LICENSE.md
flowcon-0.0.4.dist-info/METADATA
flowcon-0.0.4.dist-info/WHEEL
flowcon-0.0.4.dist-info/top_level.txt
flowcon-0.0.4.dist-info/RECORD
