Metadata-Version: 2.1
Name: flowcon
Version: 0.0.4
Summary: Normalizing flows in PyTorch. An extension of nflows.
Home-page: https://github.com/FabricioArendTorres/FlowConductor/
Author: Fabricio Arend Torres, Marcello Massimo Negri, Jonathan Aellen
License: MIT
Classifier: Programming Language :: Python :: 3
Classifier: License :: OSI Approved :: MIT License
Classifier: Operating System :: OS Independent
Classifier: Development Status :: 2 - Pre-Alpha 
License-File: LICENSE.md
Requires-Dist: matplotlib
Requires-Dist: numpy
Requires-Dist: pandas
Requires-Dist: torch
Requires-Dist: torchdiffeq
Requires-Dist: umnn
Requires-Dist: tqdm
Requires-Dist: ninja
Requires-Dist: scikit-learn
Requires-Dist: h5py
Requires-Dist: torchtestcase
Requires-Dist: parameterized
Requires-Dist: flake8
Requires-Dist: pytest
Requires-Dist: pytest-cov
Requires-Dist: black
